lugh/__init__.py
qpq-0.1.dist-info/LICENSE
qpq-0.1.dist-info/METADATA
qpq-0.1.dist-info/WHEEL
qpq-0.1.dist-info/top_level.txt
qpq-0.1.dist-info/RECORD
