Metadata-Version: 2.1
Name: qpq
Version: 0.1
Summary: Really nice lib
Home-page: https://github.com/MathieuMoalic/qpq
Author: Mathieu Moalic
Author-email: matmoa@pm.me
License: GPL-3.0
Platform: any
